customsol_pkg/__init__.py
customsol_pkg/dir_clean.py
customsol_pkg/errors.py
customsol_pkg/ftp_cleanse.py
customsol_pkg/ftp_down.py
customsol_pkg/ftp_up.py
customsol_pkg/redash_download.py
customsol_pkg/slackbot.py
customsol_pkg/supp_create.py
motolibrary-0.0.1.dist-info/LICENSE
motolibrary-0.0.1.dist-info/METADATA
motolibrary-0.0.1.dist-info/WHEEL
motolibrary-0.0.1.dist-info/top_level.txt
motolibrary-0.0.1.dist-info/RECORD
